<annotation>
	<folder>Electrolytic-capacitor</folder>
	<filename>Electrolytic-capacitor355.jpg</filename>
	<path>D:\Shreeya\projects\train\Electrolytic-capacitor\Electrolytic-capacitor355.jpg</path>
	<source>
		<database>Unknown</database>
	</source>
	<size>
		<width>256</width>
		<height>128</height>
		<depth>3</depth>
	</size>
	<segmented>0</segmented>
	<object>
		<name>Electrolytic-Capacitor</name>
		<pose>Unspecified</pose>
		<truncated>0</truncated>
		<difficult>0</difficult>
		<bndbox>
			<xmin>23</xmin>
			<ymin>3</ymin>
			<xmax>74</xmax>
			<ymax>115</ymax>
		</bndbox>
	</object>
	<object>
		<name>Electrolytic-Capacitor</name>
		<pose>Unspecified</pose>
		<truncated>0</truncated>
		<difficult>0</difficult>
		<bndbox>
			<xmin>97</xmin>
			<ymin>4</ymin>
			<xmax>147</xmax>
			<ymax>115</ymax>
		</bndbox>
	</object>
	<object>
		<name>Electrolytic-Capacitor</name>
		<pose>Unspecified</pose>
		<truncated>0</truncated>
		<difficult>0</difficult>
		<bndbox>
			<xmin>171</xmin>
			<ymin>23</ymin>
			<xmax>200</xmax>
			<ymax>114</ymax>
		</bndbox>
	</object>
	<object>
		<name>Electrolytic-Capacitor</name>
		<pose>Unspecified</pose>
		<truncated>0</truncated>
		<difficult>0</difficult>
		<bndbox>
			<xmin>213</xmin>
			<ymin>25</ymin>
			<xmax>241</xmax>
			<ymax>115</ymax>
		</bndbox>
	</object>
</annotation>
