<annotation>
	<folder>Electrolytic-capacitor</folder>
	<filename>Electrolytic-capacitor121.jpg</filename>
	<path>D:\Shreeya\projects\train\Electrolytic-capacitor\Electrolytic-capacitor121.jpg</path>
	<source>
		<database>Unknown</database>
	</source>
	<size>
		<width>256</width>
		<height>128</height>
		<depth>3</depth>
	</size>
	<segmented>0</segmented>
	<object>
		<name>Electrolytic Capacitor</name>
		<pose>Unspecified</pose>
		<truncated>1</truncated>
		<difficult>0</difficult>
		<bndbox>
			<xmin>50</xmin>
			<ymin>17</ymin>
			<xmax>256</xmax>
			<ymax>79</ymax>
		</bndbox>
	</object>
</annotation>
