<annotation>
	<folder>LED</folder>
	<filename>LED996.jpg</filename>
	<path>D:\Shreeya\projects\train\LED\LED996.jpg</path>
	<source>
		<database>Unknown</database>
	</source>
	<size>
		<width>256</width>
		<height>128</height>
		<depth>3</depth>
	</size>
	<segmented>0</segmented>
	<object>
		<name>LED</name>
		<pose>Unspecified</pose>
		<truncated>0</truncated>
		<difficult>0</difficult>
		<bndbox>
			<xmin>183</xmin>
			<ymin>13</ymin>
			<xmax>238</xmax>
			<ymax>62</ymax>
		</bndbox>
	</object>
	<object>
		<name>LED</name>
		<pose>Unspecified</pose>
		<truncated>0</truncated>
		<difficult>0</difficult>
		<bndbox>
			<xmin>61</xmin>
			<ymin>4</ymin>
			<xmax>171</xmax>
			<ymax>73</ymax>
		</bndbox>
	</object>
	<object>
		<name>LED</name>
		<pose>Unspecified</pose>
		<truncated>0</truncated>
		<difficult>0</difficult>
		<bndbox>
			<xmin>96</xmin>
			<ymin>67</ymin>
			<xmax>159</xmax>
			<ymax>112</ymax>
		</bndbox>
	</object>
	<object>
		<name>LED</name>
		<pose>Unspecified</pose>
		<truncated>1</truncated>
		<difficult>0</difficult>
		<bndbox>
			<xmin>1</xmin>
			<ymin>56</ymin>
			<xmax>84</xmax>
			<ymax>119</ymax>
		</bndbox>
	</object>
</annotation>
